<?xml version="1.0" encoding="utf-8" ?>
<dwsync>
<file name="xajax_core.js" server="www.usblogistics-corp.com.ve//httpdocs/" local="128704032440000000" remote="129208956600000000" />
<file name="xajax_core_uncompressed.js" server="www.usblogistics-corp.com.ve//httpdocs/" local="128773729720000000" remote="129208957200000000" />
<file name="xajax_debug.js" server="www.usblogistics-corp.com.ve//httpdocs/" local="128622117820000000" remote="129208957200000000" />
<file name="xajax_debug_uncompressed.js" server="www.usblogistics-corp.com.ve//httpdocs/" local="128773729720000000" remote="129208957200000000" />
<file name="xajax_lang_bg.js" server="www.usblogistics-corp.com.ve//httpdocs/" local="128624395920000000" remote="129208957200000000" />
<file name="xajax_lang_bg_uncompressed.js" server="www.usblogistics-corp.com.ve//httpdocs/" local="128773729720000000" remote="129208957200000000" />
<file name="xajax_lang_de.js" server="www.usblogistics-corp.com.ve//httpdocs/" local="128692496120000000" remote="129208957200000000" />
<file name="xajax_lang_de_uncompressed.js" server="www.usblogistics-corp.com.ve//httpdocs/" local="128692496120000000" remote="129208957200000000" />
<file name="xajax_lang_es.js" server="www.usblogistics-corp.com.ve//httpdocs/" local="128622121120000000" remote="129208957200000000" />
<file name="xajax_lang_es_uncompressed.js" server="www.usblogistics-corp.com.ve//httpdocs/" local="128773729720000000" remote="129208957200000000" />
<file name="xajax_lang_fr.js" server="www.usblogistics-corp.com.ve//httpdocs/" local="128622121120000000" remote="129208957200000000" />
<file name="xajax_lang_fr_uncompressed.js" server="www.usblogistics-corp.com.ve//httpdocs/" local="128773729720000000" remote="129208957200000000" />
<file name="xajax_lang_nl.js" server="www.usblogistics-corp.com.ve//httpdocs/" local="128692496120000000" remote="129208957200000000" />
<file name="xajax_lang_nl_uncompressed.js" server="www.usblogistics-corp.com.ve//httpdocs/" local="128692496120000000" remote="129208957200000000" />
<file name="xajax_lang_tr.js" server="www.usblogistics-corp.com.ve//httpdocs/" local="128622121120000000" remote="129208957200000000" />
<file name="xajax_lang_tr_uncompressed.js" server="www.usblogistics-corp.com.ve//httpdocs/" local="128773729720000000" remote="129208957200000000" />
<file name="xajax_legacy.js" server="www.usblogistics-corp.com.ve//httpdocs/" local="128622117820000000" remote="129208957200000000" />
<file name="xajax_legacy_uncompressed.js" server="www.usblogistics-corp.com.ve//httpdocs/" local="128773729720000000" remote="129208957200000000" />
<file name="xajax_verbose.js" server="www.usblogistics-corp.com.ve//httpdocs/" local="128622117820000000" remote="129208957200000000" />
<file name="xajax_verbose_uncompressed.js" server="www.usblogistics-corp.com.ve//httpdocs/" local="128773729720000000" remote="129208957200000000" />
</dwsync>